retl/__init__.py
retl/main.py
retl/settings.py
reiners_etl-0.2.2.dist-info/METADATA
reiners_etl-0.2.2.dist-info/WHEEL
reiners_etl-0.2.2.dist-info/entry_points.txt
reiners_etl-0.2.2.dist-info/top_level.txt
reiners_etl-0.2.2.dist-info/RECORD
