Metadata-Version: 2.4
Name: reiners-etl
Version: 0.2.2
Summary: Add your description here
Requires-Python: >=3.8
Requires-Dist: platformdirs>=2.4.0
Requires-Dist: pyyaml>=6.0.2
Requires-Dist: rclone-python>=0.1.21
Requires-Dist: rich>=13.7.0
